labelmaker/__init__.py
labelmaker/labelmaker.py
labelmaker/utility.py
labelmaker-0.3.1.dist-info/DESCRIPTION.rst
labelmaker-0.3.1.dist-info/METADATA
labelmaker-0.3.1.dist-info/RECORD
labelmaker-0.3.1.dist-info/WHEEL
labelmaker-0.3.1.dist-info/entry_points.txt
labelmaker-0.3.1.dist-info/metadata.json
labelmaker-0.3.1.dist-info/top_level.txt
