Metadata-Version: 2.0
Name: labelmaker
Version: 0.3.1
Summary: Simple labeling tool for segyio files
Home-page: UNKNOWN
Author: Statoil ASA
Author-email: fg_gpl@statoil.com
License: GPL-3.0
Platform: any
Requires-Dist: matplotlib
Requires-Dist: segyio (>=1.4)
